wagtail_svg_images/__init__.py
wagtail_svg_images/apps.py
wagtail_svg_images/blocks.py
wagtail_svg_images/migrations/__init__.py
wagtail_svg_images/models/__init__.py
wagtail_svg_images/models/fields.py
wagtail_svg_images/panels.py
wagtail_svg_images/static/js/svg_handler.js
wagtail_svg_images/templates/wagtailadmin/edit_handlers/image_or_svg_panel.html
wagtail_svg_images/templatetags/__init__.py
wagtail_svg_images/templatetags/svg_tags.py
wagtail_svg_images/wagtail_hooks.py
wagtail_svg_images-0.1.22.dist-info/WHEEL
wagtail_svg_images-0.1.22.dist-info/METADATA
wagtail_svg_images-0.1.22.dist-info/RECORD
