Metadata-Version: 2.1
Name: wagtail-svg-images
Version: 0.1.22
Summary: Workaround to support SVG as Images in Wagtail
License: MIT
Author: Ramiro A Alvarez U
Author-email: liko28s@gmail.com
Requires-Python: >=3.8,<4.0
Classifier: License :: OSI Approved :: MIT License
Classifier: Programming Language :: Python :: 3
Classifier: Programming Language :: Python :: 3.10
Classifier: Programming Language :: Python :: 3.8
Classifier: Programming Language :: Python :: 3.9
Requires-Dist: wagtail (>=3.0,<4.0)
Requires-Dist: wagtailsvg (>=0.0.33,<0.0.34)
